obiguard/__init__.py
obiguard/_obiguard_scripts.py
obiguard/py.typed
obiguard/version.py
obiguard/_vendor/__init__.py
obiguard/_vendor/openai/__init__.py
obiguard/_vendor/openai/__main__.py
obiguard/_vendor/openai/_base_client.py
obiguard/_vendor/openai/_client.py
obiguard/_vendor/openai/_compat.py
obiguard/_vendor/openai/_constants.py
obiguard/_vendor/openai/_exceptions.py
obiguard/_vendor/openai/_files.py
obiguard/_vendor/openai/_legacy_response.py
obiguard/_vendor/openai/_models.py
obiguard/_vendor/openai/_module_client.py
obiguard/_vendor/openai/_qs.py
obiguard/_vendor/openai/_resource.py
obiguard/_vendor/openai/_response.py
obiguard/_vendor/openai/_streaming.py
obiguard/_vendor/openai/_types.py
obiguard/_vendor/openai/_version.py
obiguard/_vendor/openai/pagination.py
obiguard/_vendor/openai/py.typed
obiguard/_vendor/openai/version.py
obiguard/_vendor/openai/_extras/__init__.py
obiguard/_vendor/openai/_extras/_common.py
obiguard/_vendor/openai/_extras/numpy_proxy.py
obiguard/_vendor/openai/_extras/pandas_proxy.py
obiguard/_vendor/openai/_extras/sounddevice_proxy.py
obiguard/_vendor/openai/_utils/__init__.py
obiguard/_vendor/openai/_utils/_logs.py
obiguard/_vendor/openai/_utils/_proxy.py
obiguard/_vendor/openai/_utils/_reflection.py
obiguard/_vendor/openai/_utils/_streams.py
obiguard/_vendor/openai/_utils/_sync.py
obiguard/_vendor/openai/_utils/_transform.py
obiguard/_vendor/openai/_utils/_typing.py
obiguard/_vendor/openai/_utils/_utils.py
obiguard/_vendor/openai/cli/__init__.py
obiguard/_vendor/openai/cli/_cli.py
obiguard/_vendor/openai/cli/_errors.py
obiguard/_vendor/openai/cli/_models.py
obiguard/_vendor/openai/cli/_progress.py
obiguard/_vendor/openai/cli/_utils.py
obiguard/_vendor/openai/cli/_api/__init__.py
obiguard/_vendor/openai/cli/_api/_main.py
obiguard/_vendor/openai/cli/_api/audio.py
obiguard/_vendor/openai/cli/_api/completions.py
obiguard/_vendor/openai/cli/_api/files.py
obiguard/_vendor/openai/cli/_api/image.py
obiguard-1.0.19.dist-info/licenses/LICENSE
obiguard-1.0.19.dist-info/METADATA
obiguard-1.0.19.dist-info/WHEEL
obiguard-1.0.19.dist-info/top_level.txt
obiguard-1.0.19.dist-info/zip-safe
obiguard-1.0.19.dist-info/RECORD
