Metadata-Version: 2.4
Name: obiguard
Version: 1.0.19
Summary: Python SDK for Obiguard
Home-page: https://github.com/Obiguard-AI/obiguard-python-sdk
Author: obiguard.com
Author-email: support@obiguard.com
Requires-Python: >=3.9
License-File: LICENSE
Requires-Dist: obiguard-trace-python-sdk>=3.8.26
Dynamic: license-file
